{
  "pages": [
    {
      "url": "https://johnniebrowns.com/contact",
      "is_candidate": false,
      "has_email": true,
      "text": "CONTACT US\nRESERVATION & BOOKING INQUIRIES\nadam@johnniebrowns.com\nPUBLIC RELATIONS\ncaroline@menin.com\nBegin Constant Contact Inline Form Code\nEnd Constant Contact Inline Form Code\nCONTACT US\nRESERVATION & BOOKING INQUIRIES\nadam@johnniebrowns.com\nPUBLIC RELATIONS\ncaroline@menin.com\nBegin Constant Contact Inline Form Code\nEnd Constant Contact Inline Form Code\nCONTACT US\nRESERVATION & BOOKING INQUIRIES\nadam@johnniebrowns.com\nPUBLIC RELATIONS\ncaroline@menin.com\nBegin Constant Contact Inline Form Code\nEnd Constant Contact Inline Form Code\nLOCATION\n301 E Atlantic Ave.\nDelray Beach, FL 33483\n(561) 243-9911\nHOURS\nMonday-Thursday:\n5pm-CLOSE\nFriday\n:\n4pm-CLOSE\nSaturdays & Sundays:\n12:00PM - CLOSE",
      "emails": [
        "adam@johnniebrowns.com",
        "caroline@menin.com",
        "info@johnniebrowns.com",
        "user@domain.com"
      ]
    }
  ],
  "all_links": [
    "https://johnniebrowns.com/",
    "https://johnniebrowns.com/cart",
    "https://johnniebrowns.com/careers",
    "https://johnniebrowns.com/menu",
    "https://johnniebrowns.com/events",
    "https://johnniebrowns.com/happenings",
    "https://johnniebrowns.com/contact",
    "https://johnniebrowns.com/group-dining"
  ],
  "candidate_links": [
    "https://johnniebrowns.com/contact"
  ],
  "visited": [
    "https://johnniebrowns.com/",
    "https://johnniebrowns.com/about",
    "https://johnniebrowns.com/contact",
    "https://johnniebrowns.com/staff",
    "https://johnniebrowns.com/team",
    "https://johnniebrowns.com/board",
    "https://johnniebrowns.com/directory",
    "https://johnniebrowns.com/events",
    "https://johnniebrowns.com/sitemap.xml",
    "https://johnniebrowns.com/council",
    "https://johnniebrowns.com/leadership",
    "https://johnniebrowns.com/management",
    "https://johnniebrowns.com/producers",
    "https://johnniebrowns.com/support",
    "https://johnniebrowns.com/crew",
    "https://johnniebrowns.com/members",
    "https://johnniebrowns.com/bios",
    "https://johnniebrowns.com/people",
    "https://johnniebrowns.com/artists",
    "https://johnniebrowns.com/musicians",
    "https://johnniebrowns.com/faculty",
    "https://johnniebrowns.com/administration",
    "https://johnniebrowns.com/contact"
  ],
  "base_url": "https://johnniebrowns.com/"
}