{
  "pages": [],
  "all_links": [
    "http://www.parkeastclub.com/"
  ],
  "candidate_links": [],
  "visited": [
    "http://www.parkeastclub.com/",
    "http://www.parkeastclub.com/about",
    "http://www.parkeastclub.com/contact",
    "http://www.parkeastclub.com/staff",
    "http://www.parkeastclub.com/team",
    "http://www.parkeastclub.com/board",
    "http://www.parkeastclub.com/directory",
    "http://www.parkeastclub.com/events",
    "http://www.parkeastclub.com/sitemap.xml",
    "http://www.parkeastclub.com/council",
    "http://www.parkeastclub.com/leadership",
    "http://www.parkeastclub.com/management",
    "http://www.parkeastclub.com/producers",
    "http://www.parkeastclub.com/support",
    "http://www.parkeastclub.com/crew",
    "http://www.parkeastclub.com/members",
    "http://www.parkeastclub.com/bios",
    "http://www.parkeastclub.com/people",
    "http://www.parkeastclub.com/artists",
    "http://www.parkeastclub.com/musicians",
    "http://www.parkeastclub.com/faculty",
    "http://www.parkeastclub.com/administration"
  ],
  "base_url": "http://www.parkeastclub.com/"
}