{
  "pages": [
    {
      "url": "https://facebook.com/TheSoundBarTally",
      "is_candidate": false,
      "has_email": false,
      "text": "",
      "emails": []
    },
    {
      "url": "https://www.facebook.com/131774063356450",
      "is_candidate": false,
      "has_email": false,
      "text": "",
      "emails": []
    }
  ],
  "all_links": [
    "http://www.thesoundbartallahassee.com/show-schedule",
    "http://www.thesoundbartallahassee.com/sounds-of-the-blues-fest",
    "http://www.thesoundbartallahassee.com/m/create-account",
    "http://www.thesoundbartallahassee.com/m/orders",
    "http://www.thesoundbartallahassee.com/",
    "http://www.thesoundbartallahassee.com/m/account",
    "http://www.thesoundbartallahassee.com/blank",
    "http://www.thesoundbartallahassee.com/booking"
  ],
  "candidate_links": [
    "https://facebook.com/TheSoundBarTally",
    "https://www.facebook.com/131774063356450"
  ],
  "visited": [
    "http://www.thesoundbartallahassee.com/",
    "http://www.thesoundbartallahassee.com/about",
    "http://www.thesoundbartallahassee.com/contact",
    "http://www.thesoundbartallahassee.com/staff",
    "http://www.thesoundbartallahassee.com/team",
    "http://www.thesoundbartallahassee.com/board",
    "http://www.thesoundbartallahassee.com/directory",
    "http://www.thesoundbartallahassee.com/events",
    "http://www.thesoundbartallahassee.com/sitemap.xml",
    "http://www.thesoundbartallahassee.com/council",
    "http://www.thesoundbartallahassee.com/leadership",
    "http://www.thesoundbartallahassee.com/management",
    "http://www.thesoundbartallahassee.com/producers",
    "http://www.thesoundbartallahassee.com/support",
    "http://www.thesoundbartallahassee.com/crew",
    "http://www.thesoundbartallahassee.com/members",
    "http://www.thesoundbartallahassee.com/bios",
    "http://www.thesoundbartallahassee.com/people",
    "http://www.thesoundbartallahassee.com/artists",
    "http://www.thesoundbartallahassee.com/musicians",
    "http://www.thesoundbartallahassee.com/faculty",
    "http://www.thesoundbartallahassee.com/administration",
    "https://facebook.com/TheSoundBarTally",
    "https://www.facebook.com/131774063356450"
  ],
  "base_url": "http://www.thesoundbartallahassee.com/"
}