{
  "pages": [
    {
      "url": "http://windwardislepark.com/#about",
      "is_candidate": false,
      "has_email": true,
      "text": "Windward Isle RV and Mobile Home Park\nA 55+ community located in Sarasota, Florida operated by 157 park shareholders.\nOffering seasonal RV hookups.\nNo Dogs Allowed!\nGetting to Know Windward Isle\nWelcome to our vibrant community, meticulously designed for active seniors who crave the perfect balance of relaxation and excitement in their lives. So, go ahead and immerse yourself in the countless amenities we offer, and let the adventure begin!\nRelaxing Pool area\nFind relaxation in our heated, saltwater pool area with ample seating.\nThe clubhouse\nEnjoy dancing, cards, pool table, ping pong, jam sessions and more.\nOutdoor recreation\nWe have cornhole, shuffleboard, bocce ball, and pickleball.\nGetting to Know Windward Isle\nWelcome to our vibrant community, meticulously designed for active seniors who crave the perfect balance of relaxation and excitement in their lives. So, go ahead and immerse yourself in the countless amenities we offer, and let the adventure begin!\nRelaxing Pool area\nFind relaxation in our heated, saltwater pool area with ample seating.\nThe clubhouse\nEnjoy dancing, cards, pool table, ping pong, jam sessions and more.\nOutdoor recreation\nWe have cornhole, shuffleboard, bocce ball, and pickleball.\nWindward Isle Gallery\nView pictures of our facilities.\nAll\nRecreation\nPool\nOther\nSeasonal RV Rates\nUpdated March 2024\n[Sold Out Through April 2024]\n- We do not accept Good Sam, Passport America, or any other club membership.\n- Starting january 1st 2025, incoming rvs must be newer than 15 years old.\nJanuary 1 - March 31, 2024\nDaily - $75\nWeekly - $490\nMonthly - $1,300\nMay 1 - October 31, 2024\nDaily - $65\nWeekly - $375\nMonthly - $800\nApril & November 1 - December 31, 2024\nDaily - $70\nWeekly - $490\nMonthly - $1,000\nRV Specs\n55+ RV Community\n50 Amp Services Available\nJanuary 1 - March 31, 2024\nDaily - $75\nWeekly - $490\nMonthly - $1,300\nMay 1 - October 31, 2024\nDaily - $65\nWeekly - $375\nMonthly - $800\nApril & November 1 - December 31, 2024\nDaily - $70\nWeekly - $490\nMonthly - $1,000\nRV Specs\n55+ RV Community\n50 Amp Services Available\nHomes for Sale\nJoin our 55+ community by purchasing a home and becoming a shareholder.\nLot #253\n⚫ Asking $210,000\n⚫ 1972\n⚫ 2 Bed / 2 Bath\n⚫ Has been updated.\nCall 941-662-7782 to make an offer.\nRVs & Park Models for Sale\nLease an RV lot.\nLot #34\n⚫ Asking $54,000\n⚫ 2003 Franklin Park Model\n⚫ New Central Air/Heat\n⚫ Washer and Dryer Included\n⚫ Newer Roof with Guarantee\n⚫ All Furniture and 1 TV Included\nCall 513-623-7535 to make an offer.\nLot #10\n⚫ Asking $19,800\n⚫ Salem Model, 2010\n⚫ 1 bed / 1 bath\n⚫New Awning and Screen\n⚫ Full Size Fridge\nCall 941-504-4333 to make an offer.\nHomes for Sale\nJoin our 55+ community by purchasing a home and becoming a shareholder.\nLot #253\n⚫ Asking $210,000\n⚫ 1972\n⚫ 2 Bed / 2 Bath\n⚫ Has been updated.\nCall 941-662-7782 to make an offer.\nRVs & Park Models for Sale\nLease an RV lot.\nLot #34\n⚫ Asking $54,000\n⚫ 2003 Franklin Park Model\n⚫ New Central Air/Heat\n⚫ Washer and Dryer Included\n⚫ Newer Roof with Guarantee\n⚫ All Furniture and 1 TV Included\nCall 513-623-7535 to make an offer.\nLot #10\n⚫ Asking $19,800\n⚫ Salem Model, 2010\n⚫ 1 bed / 1 bath\n⚫New Awning and Screen\n⚫ Full Size Fridge\nCall 941-504-4333 to make an offer.\nLot #253\n⚫ Asking $210,000\n⚫ 1972\n⚫ 2 Bed / 2 Bath\n⚫ Has been updated.\nCall 941-662-7782 to make an offer.\nLot #34\n⚫ Asking $54,000\n⚫ 2003 Franklin Park Model\n⚫ New Central Air/Heat\n⚫ Washer and Dryer Included\n⚫ Newer Roof with Guarantee\n⚫ All Furniture and 1 TV Included\nCall 513-623-7535 to make an offer.\nLot #10\n⚫ Asking $19,800\n⚫ Salem Model, 2010\n⚫ 1 bed / 1 bath\n⚫New Awning and Screen\n⚫ Full Size Fridge\nCall 941-504-4333 to make an offer.\nOur Rules\nEmbracing Serenity at Our 55+ RV Park: Our Standards for a Clean, Safe, and Well-Organized Community\nRV Rules\nRV Rules updated 5/21/24\nShareholder Rules\nOur Rules\nEmbracing Serenity at Our 55+ RV Park: Our Standards for a Clean, Safe, and Well-Organized Community\nRV Rules\nRV Rules updated 5/21/24\nShareholder Rules\nPhone\n1-941-922-3090\nEmail\nwwisrq@gmail.com\nAddress\n#1 Catamaran Drive\nSarasota, Florida 34233\nContact Us\nReach out if you have questions about Windward Isle or you're interested in seasonal renting or living at Windward Isle as a part owner of the park.\nYour Name\nYour Email\nLeave a Message\nSend\nPhone\n1-941-922-3090\nEmail\nwwisrq@gmail.com\nAddress\n#1 Catamaran Drive\nSarasota, Florida 34233\nContact Us\nReach out if you have questions about Windward Isle or you're interested in seasonal renting or living at Windward Isle as a part owner of the park.\nYour Name\nYour Email\nLeave a Message\nSend\nWindward Isle RV and Mobile Home Park\n55+ Community Located in Sarasota, Florida",
      "emails": [
        "wwisrq@gmail.com"
      ]
    },
    {
      "url": "http://windwardislepark.com/#contact",
      "is_candidate": false,
      "has_email": true,
      "text": "Windward Isle RV and Mobile Home Park\nA 55+ community located in Sarasota, Florida operated by 157 park shareholders.\nOffering seasonal RV hookups.\nNo Dogs Allowed!\nGetting to Know Windward Isle\nWelcome to our vibrant community, meticulously designed for active seniors who crave the perfect balance of relaxation and excitement in their lives. So, go ahead and immerse yourself in the countless amenities we offer, and let the adventure begin!\nRelaxing Pool area\nFind relaxation in our heated, saltwater pool area with ample seating.\nThe clubhouse\nEnjoy dancing, cards, pool table, ping pong, jam sessions and more.\nOutdoor recreation\nWe have cornhole, shuffleboard, bocce ball, and pickleball.\nGetting to Know Windward Isle\nWelcome to our vibrant community, meticulously designed for active seniors who crave the perfect balance of relaxation and excitement in their lives. So, go ahead and immerse yourself in the countless amenities we offer, and let the adventure begin!\nRelaxing Pool area\nFind relaxation in our heated, saltwater pool area with ample seating.\nThe clubhouse\nEnjoy dancing, cards, pool table, ping pong, jam sessions and more.\nOutdoor recreation\nWe have cornhole, shuffleboard, bocce ball, and pickleball.\nWindward Isle Gallery\nView pictures of our facilities.\nAll\nRecreation\nPool\nOther\nSeasonal RV Rates\nUpdated March 2024\n[Sold Out Through April 2024]\n- We do not accept Good Sam, Passport America, or any other club membership.\n- Starting january 1st 2025, incoming rvs must be newer than 15 years old.\nJanuary 1 - March 31, 2024\nDaily - $75\nWeekly - $490\nMonthly - $1,300\nMay 1 - October 31, 2024\nDaily - $65\nWeekly - $375\nMonthly - $800\nApril & November 1 - December 31, 2024\nDaily - $70\nWeekly - $490\nMonthly - $1,000\nRV Specs\n55+ RV Community\n50 Amp Services Available\nJanuary 1 - March 31, 2024\nDaily - $75\nWeekly - $490\nMonthly - $1,300\nMay 1 - October 31, 2024\nDaily - $65\nWeekly - $375\nMonthly - $800\nApril & November 1 - December 31, 2024\nDaily - $70\nWeekly - $490\nMonthly - $1,000\nRV Specs\n55+ RV Community\n50 Amp Services Available\nHomes for Sale\nJoin our 55+ community by purchasing a home and becoming a shareholder.\nLot #253\n⚫ Asking $210,000\n⚫ 1972\n⚫ 2 Bed / 2 Bath\n⚫ Has been updated.\nCall 941-662-7782 to make an offer.\nRVs & Park Models for Sale\nLease an RV lot.\nLot #34\n⚫ Asking $54,000\n⚫ 2003 Franklin Park Model\n⚫ New Central Air/Heat\n⚫ Washer and Dryer Included\n⚫ Newer Roof with Guarantee\n⚫ All Furniture and 1 TV Included\nCall 513-623-7535 to make an offer.\nLot #10\n⚫ Asking $19,800\n⚫ Salem Model, 2010\n⚫ 1 bed / 1 bath\n⚫New Awning and Screen\n⚫ Full Size Fridge\nCall 941-504-4333 to make an offer.\nHomes for Sale\nJoin our 55+ community by purchasing a home and becoming a shareholder.\nLot #253\n⚫ Asking $210,000\n⚫ 1972\n⚫ 2 Bed / 2 Bath\n⚫ Has been updated.\nCall 941-662-7782 to make an offer.\nRVs & Park Models for Sale\nLease an RV lot.\nLot #34\n⚫ Asking $54,000\n⚫ 2003 Franklin Park Model\n⚫ New Central Air/Heat\n⚫ Washer and Dryer Included\n⚫ Newer Roof with Guarantee\n⚫ All Furniture and 1 TV Included\nCall 513-623-7535 to make an offer.\nLot #10\n⚫ Asking $19,800\n⚫ Salem Model, 2010\n⚫ 1 bed / 1 bath\n⚫New Awning and Screen\n⚫ Full Size Fridge\nCall 941-504-4333 to make an offer.\nLot #253\n⚫ Asking $210,000\n⚫ 1972\n⚫ 2 Bed / 2 Bath\n⚫ Has been updated.\nCall 941-662-7782 to make an offer.\nLot #34\n⚫ Asking $54,000\n⚫ 2003 Franklin Park Model\n⚫ New Central Air/Heat\n⚫ Washer and Dryer Included\n⚫ Newer Roof with Guarantee\n⚫ All Furniture and 1 TV Included\nCall 513-623-7535 to make an offer.\nLot #10\n⚫ Asking $19,800\n⚫ Salem Model, 2010\n⚫ 1 bed / 1 bath\n⚫New Awning and Screen\n⚫ Full Size Fridge\nCall 941-504-4333 to make an offer.\nOur Rules\nEmbracing Serenity at Our 55+ RV Park: Our Standards for a Clean, Safe, and Well-Organized Community\nRV Rules\nRV Rules updated 5/21/24\nShareholder Rules\nOur Rules\nEmbracing Serenity at Our 55+ RV Park: Our Standards for a Clean, Safe, and Well-Organized Community\nRV Rules\nRV Rules updated 5/21/24\nShareholder Rules\nPhone\n1-941-922-3090\nEmail\nwwisrq@gmail.com\nAddress\n#1 Catamaran Drive\nSarasota, Florida 34233\nContact Us\nReach out if you have questions about Windward Isle or you're interested in seasonal renting or living at Windward Isle as a part owner of the park.\nYour Name\nYour Email\nLeave a Message\nSend\nPhone\n1-941-922-3090\nEmail\nwwisrq@gmail.com\nAddress\n#1 Catamaran Drive\nSarasota, Florida 34233\nContact Us\nReach out if you have questions about Windward Isle or you're interested in seasonal renting or living at Windward Isle as a part owner of the park.\nYour Name\nYour Email\nLeave a Message\nSend\nWindward Isle RV and Mobile Home Park\n55+ Community Located in Sarasota, Florida",
      "emails": [
        "wwisrq@gmail.com"
      ]
    }
  ],
  "all_links": [
    "https://windwardislepark.com/wp-content/uploads/2023/04/IMG_7723-scaled.jpg",
    "https://windwardislepark.com/wp-content/uploads/2023/04/pool-pic.png",
    "https://windwardislepark.com/wp-content/uploads/2023/05/Jam-Session.jpg",
    "http://windwardislepark.com/#about",
    "https://windwardislepark.com/wp-content/uploads/2023/04/IMG_7746-scaled.jpg",
    "https://windwardislepark.com/wp-content/uploads/2023/04/IMG_7740-scaled.jpg",
    "https://windwardislepark.com/wp-content/uploads/2023/09/IMG-4626.jpg",
    "https://windwardislepark.com/wp-content/uploads/2023/05/Craft-Show.jpg",
    "https://windwardislepark.com/wp-content/uploads/2023/04/IMG_7713-scaled.jpg",
    "https://windwardislepark.com/wp-content/uploads/2023/05/pickelball-hit.jpg",
    "https://windwardislepark.com/",
    "https://windwardislepark.com/wp-content/uploads/2023/04/IMG_7728-scaled.jpg",
    "http://windwardislepark.com/#rules",
    "https://windwardislepark.com/wp-content/uploads/2023/04/IMG_7718-scaled.jpg",
    "https://windwardislepark.com",
    "https://windwardislepark.com/wp-content/uploads/2023/05/Recreation-rotated.jpg",
    "https://windwardislepark.com/wp-content/uploads/2024/03/Resized_20240221_085455.jpeg",
    "https://windwardislepark.com/wp-content/uploads/2023/05/Bocce.jpg",
    "https://windwardislepark.com/wp-content/uploads/2023/04/IMG_7725-scaled.jpg",
    "https://windwardislepark.com/wp-content/uploads/2023/04/IMG_7726-scaled.jpg",
    "http://windwardislepark.com/#contact",
    "https://windwardislepark.com/wp-content/uploads/2023/04/IMG_7737-scaled.jpg",
    "https://windwardislepark.com/wp-content/uploads/2023/05/Cornhole.jpg",
    "https://windwardislepark.com/wp-content/uploads/2023/04/IMG_7732-scaled.jpg",
    "http://windwardislepark.com/#rv-rates",
    "http://windwardislepark.com/#gallery",
    "https://windwardislepark.com/wp-content/uploads/2023/05/Pickelball.jpg",
    "https://windwardislepark.com/wp-content/uploads/2023/04/IMG_7743-scaled.jpg"
  ],
  "candidate_links": [
    "http://windwardislepark.com/#about",
    "http://windwardislepark.com/#contact"
  ],
  "visited": [
    "http://windwardislepark.com/",
    "http://windwardislepark.com/about",
    "http://windwardislepark.com/contact",
    "http://windwardislepark.com/staff",
    "http://windwardislepark.com/team",
    "http://windwardislepark.com/board",
    "http://windwardislepark.com/directory",
    "http://windwardislepark.com/events",
    "http://windwardislepark.com/sitemap.xml",
    "http://windwardislepark.com/council",
    "http://windwardislepark.com/leadership",
    "http://windwardislepark.com/management",
    "http://windwardislepark.com/producers",
    "http://windwardislepark.com/support",
    "http://windwardislepark.com/crew",
    "http://windwardislepark.com/members",
    "http://windwardislepark.com/bios",
    "http://windwardislepark.com/people",
    "http://windwardislepark.com/artists",
    "http://windwardislepark.com/musicians",
    "http://windwardislepark.com/faculty",
    "http://windwardislepark.com/administration",
    "http://windwardislepark.com/#about",
    "http://windwardislepark.com/#contact"
  ],
  "base_url": "http://windwardislepark.com/"
}