{
  "timestamp": "2025-09-20T18:53:10.135906",
  "content": {
    "lusha": {
      "status": "ok",
      "last_check": "2025-09-20T18:53:06.773865",
      "company": {
        "name": null,
        "domain": "emeraldcoastmarine.com",
        "website": null,
        "linkedin_url": null,
        "industry": null,
        "size": null,
        "country": null,
        "headquarter": null,
        "founded_at": null,
        "revenue": null,
        "logo_url": null,
        "locations": null,
        "type": null,
        "specialties": null
      },
      "raw": {
        "data": {
          "id": 3887766,
          "description": "Welcome to Emerald Coast Marine Group\nNorthwest Florida’s Premier, All-Inclusive Marine Experience!\nEmerald Coast Marine Group is very pleased to offer two convenient locations to serve the needs of our valued area boaters.\n\nOur headquarters location in the Niceville/Destin, FL market is nestled on the north side of the Choctawhatchee Bay. It features a full-service marine center including a newly constructed dry stack storage facility, marina with wet slips, plus new and premium pre-owned boat sales, yacht and brokerage division, parts and service department, yacht club, boat club, and waterfront restaurant and bar.\n\nOur newest sales location in Orange Beach, AL is situated at The Wharf in a 6000-square foot facility with inviting tropical, open-air showroom featuring a display of new and premium owned boats, along with brokerage and consignment units.\n\nEmerald Coast Marine Group is locally-owned and operated by boating enthusiasts dedicated to delivering the ultimate, all-inclusive marine experience! As our earned Five-Star customer rating attests, each member of the Emerald Coast Marine Team reflects and embodies an unprecedented commitment to our customers.  We invite you to tour both of our facilities, experience our genuine Southern hospitality and meet the members of our team. Come discover why we believe … Life is Better with a Boat!",
          "domain": "emeraldcoastmarine.com",
          "employees": "11 - 50",
          "founded": "2016",
          "fqdn": "www.emeraldcoastmarine.com",
          "logoUrl": "https://logo.lusha.co/coresignal/202405/d/11/d1156bce490bb9f5580dfbc37022251f",
          "name": "Emerald Coast Marine",
          "revenueRange": [
            10000000,
            50000000
          ],
          "mainIndustry": "Transportation, Logistics, Supply Chain & Storage",
          "subIndustry": "Maritime Transportation",
          "social": {
            "linkedin": {
              "url": "https://www.linkedin.com/company/emerald-coast-marine-inc"
            }
          },
          "address": "Niceville North America United States US 115 John Sims Parkway West; Niceville, Florida 32578, US Florida FL -86.48217010498047,30.51685905456543 ",
          "location": {
            "city": "Niceville",
            "country": "United States",
            "fullLocation": "Niceville North America United States US 115 John Sims Parkway West; Niceville, Florida 32578, US Florida FL -86.48217010498047,30.51685905456543 ",
            "state": "Florida",
            "stateCode": "US",
            "countryIso2": "US",
            "rawLocation": "115 John Sims Parkway West; Niceville, Florida 32578, US"
          },
          "industryPrimaryGroupDetails": {
            "sics": [
              {
                "sic": 4412,
                "description": "Deep sea foreign transportation of freight"
              }
            ],
            "naics": [
              {
                "naics": 483112,
                "description": "Deep Sea Passenger Transportation"
              }
            ]
          },
          "website": "https://emeraldcoastmarine.com"
        },
        "meta": {}
      }
    },
    "contactout": {
      "status": "ok",
      "last_check": "2025-09-20T18:53:07.923045",
      "company": {
        "name": "Test",
        "domain": "test.com",
        "website": "http://test.com",
        "linkedin_url": "https://www.linkedin.com/company/test",
        "industry": "Computer Software",
        "size": 89,
        "country": "United States",
        "headquarter": "San Francisco, US",
        "founded_at": 2015,
        "revenue": "$5.4M",
        "logo_url": "https://images.contactout.com/companies/328ffa89a83a83042329f8181b7fbfaf",
        "locations": [
          "San Francisco, US"
        ],
        "type": "Privately Held",
        "specialties": []
      },
      "raw": {
        "message": "This is a sample response. To unlock full access, please book a call with our sales team: https://contactout.com/meeting?utm_source=api-access",
        "status_code": 200,
        "companies": [
          {
            "contactout.com": {
              "li_vanity": "https://www.linkedin.com/company/test",
              "name": "Test",
              "domain": "test.com",
              "description": "This company specializes in innovative software solutions to streamline business operations and enhance productivity.",
              "website": "http://test.com",
              "logo_url": "https://images.contactout.com/companies/328ffa89a83a83042329f8181b7fbfaf",
              "type": "Privately Held",
              "headquarter": "San Francisco, US",
              "country": "United States",
              "size": 89,
              "founded_at": 2015,
              "locations": [
                "San Francisco, US"
              ],
              "industry": "Computer Software",
              "specialties": [],
              "revenue": "$5.4M"
            }
          }
        ]
      }
    },
    "rocketreach": {
      "status": "unauthorized",
      "last_check": "2025-09-20T18:53:10.132297",
      "http_status": 403,
      "message": "Clave inválida o plan sin acceso"
    }
  }
}