{
  "site_url": "https://ascensionpilates.com/",
  "domain": "ascensionpilates.com",
  "version": 3,
  "band_keywords": [
    "live music",
    "concert",
    "event",
    "show",
    "gig",
    "performance",
    "book a band",
    "booking",
    "music booking",
    "hire a band",
    "reserve a band",
    "stage",
    "sound system",
    "audio equipment",
    "lighting",
    "stage rental",
    "weekly music",
    "monthly music",
    "calendar",
    "schedule",
    "lineup",
    "music venue",
    "band night",
    "open mic",
    "live performance",
    "dj set",
    "bands",
    "performers",
    "artists",
    "acts",
    "music night",
    "tribute band",
    "local band",
    "beer garden",
    "patio music",
    "outdoor stage",
    "indoor stage",
    "música en vivo",
    "concierto",
    "evento",
    "escenario",
    "banda",
    "espectáculo"
  ],
  "sitemap_sample": [
    "https://ascensionpilates.com/",
    "https://ascensionpilates.com/events",
    "https://ascensionpilates.com/our-team",
    "https://ascensionpilates.com/contact-us",
    "https://ascensionpilates.com/faq",
    "https://ascensionpilates.com/class-schedule",
    "https://ascensionpilates.com/pricing",
    "https://ascensionpilates.com/on-demand",
    "https://ascensionpilates.com/blog",
    "https://ascensionpilates.com/1-1-training",
    "https://ascensionpilates.com/careers",
    "https://ascensionpilates.com/community",
    "https://ascensionpilates.com/building-strength-in-community",
    "https://ascensionpilates.com/you-deserve-to-feel-like-you-again",
    "https://ascensionpilates.com/the-healing-power-of-holistic-wellness",
    "https://ascensionpilates.com/the-6-principles-of-pilates-where-mindfulness-meets-movement",
    "https://ascensionpilates.com/motherhood-and-movement-finding-strength-for-you-and-your-little-one",
    "https://ascensionpilates.com/how-often-should-i-work-out-and-what-is-the-sweet-spot",
    "https://ascensionpilates.com/what-is-mat-pilates-and-why-should-you-try-it",
    "https://ascensionpilates.com/mommy---me"
  ],
  "candidates": [
    "https://ascensionpilates.com/contact-us",
    "https://ascensionpilates.com/our-team",
    "https://ascensionpilates.com/events",
    "https://ascensionpilates.com/faq",
    "https://ascensionpilates.com/",
    "https://ascensionpilates.com/class-schedule",
    "https://ascensionpilates.com/contact",
    "https://ascensionpilates.com/contact/",
    "https://ascensionpilates.com/contact-us/",
    "https://ascensionpilates.com/contactus",
    "https://ascensionpilates.com/contactus/",
    "https://ascensionpilates.com/about",
    "https://ascensionpilates.com/about/",
    "https://ascensionpilates.com/about-us",
    "https://ascensionpilates.com/about-us/",
    "https://ascensionpilates.com/visit",
    "https://ascensionpilates.com/visit/",
    "https://ascensionpilates.com/location",
    "https://ascensionpilates.com/location/",
    "https://ascensionpilates.com/directions",
    "https://ascensionpilates.com/directions/"
  ],
  "per_page": {
    "https://ascensionpilates.com/contact-us": {
      "title": "ASCENSION PILATES | Contact Us",
      "band_hits": {
        "event": {
          "total": 3,
          "zones": {
            "title": 0,
            "body": 3,
            "menu": 0,
            "footer": 0
          },
          "pages": [
            "https://ascensionpilates.com/contact-us"
          ]
        }
      },
      "emails": [
        "info@ascensionpilates.com",
        "questions.info@ascensionpilates.com"
      ],
      "phones": [
        "352-287-2323",
        "555-555-5555"
      ],
      "socials": [
        "http://instagram.com/",
        "https://facebook.com/",
        "https://www.facebook.com/people/Ascension-Pilates-Wellness/61573952457965/",
        "https://www.instagram.com/ascensionpilates/"
      ]
    },
    "https://ascensionpilates.com/our-team": {
      "title": "ASCENSION PILATES | Our Team",
      "band_hits": {
        "event": {
          "total": 3,
          "zones": {
            "title": 0,
            "body": 3,
            "menu": 0,
            "footer": 0
          },
          "pages": [
            "https://ascensionpilates.com/our-team"
          ]
        }
      },
      "emails": [
        "info@ascensionpilates.com",
        "questions.info@ascensionpilates.com"
      ],
      "phones": [
        "352-287-2323",
        "555-555-5555"
      ],
      "socials": [
        "https://www.facebook.com/people/Ascension-Pilates-Wellness/61573952457965/",
        "https://www.instagram.com/ascensionpilates/"
      ]
    },
    "https://ascensionpilates.com/events": {
      "title": "ASCENSION PILATES | Events",
      "band_hits": {
        "event": {
          "total": 7,
          "zones": {
            "title": 1,
            "body": 6,
            "menu": 0,
            "footer": 0
          },
          "pages": [
            "https://ascensionpilates.com/events"
          ]
        },
        "calendar": {
          "total": 1,
          "zones": {
            "title": 0,
            "body": 1,
            "menu": 0,
            "footer": 0
          },
          "pages": [
            "https://ascensionpilates.com/events"
          ]
        },
        "schedule": {
          "total": 1,
          "zones": {
            "title": 0,
            "body": 1,
            "menu": 0,
            "footer": 0
          },
          "pages": [
            "https://ascensionpilates.com/events"
          ]
        }
      },
      "emails": [
        "info@ascensionpilates.com",
        "questions.info@ascensionpilates.com"
      ],
      "phones": [
        "352-287-2323",
        "555-555-5555"
      ],
      "socials": [
        "https://www.facebook.com/people/Ascension-Pilates-Wellness/61573952457965/",
        "https://www.instagram.com/ascensionpilates/"
      ]
    },
    "https://ascensionpilates.com/faq": {
      "title": "ASCENSION PILATES | FAQ",
      "band_hits": {
        "event": {
          "total": 3,
          "zones": {
            "title": 0,
            "body": 3,
            "menu": 0,
            "footer": 0
          },
          "pages": [
            "https://ascensionpilates.com/faq"
          ]
        }
      },
      "emails": [
        "info@ascensionpilates.com",
        "questions.info@ascensionpilates.com"
      ],
      "phones": [
        "352-287-2323",
        "555-555-5555"
      ],
      "socials": [
        "https://www.facebook.com/people/Ascension-Pilates-Wellness/61573952457965/",
        "https://www.instagram.com/ascensionpilates/"
      ]
    },
    "https://ascensionpilates.com/": {
      "title": "ASCENSION PILATES & WELLNESS",
      "band_hits": {
        "event": {
          "total": 6,
          "zones": {
            "title": 0,
            "body": 6,
            "menu": 0,
            "footer": 0
          },
          "pages": [
            "https://ascensionpilates.com/"
          ]
        },
        "show": {
          "total": 13,
          "zones": {
            "title": 0,
            "body": 13,
            "menu": 0,
            "footer": 0
          },
          "pages": [
            "https://ascensionpilates.com/"
          ]
        },
        "gig": {
          "total": 1,
          "zones": {
            "title": 0,
            "body": 1,
            "menu": 0,
            "footer": 0
          },
          "pages": [
            "https://ascensionpilates.com/"
          ]
        },
        "booking": {
          "total": 4,
          "zones": {
            "title": 0,
            "body": 4,
            "menu": 0,
            "footer": 0
          },
          "pages": [
            "https://ascensionpilates.com/"
          ]
        },
        "calendar": {
          "total": 2,
          "zones": {
            "title": 0,
            "body": 2,
            "menu": 0,
            "footer": 0
          },
          "pages": [
            "https://ascensionpilates.com/"
          ]
        },
        "schedule": {
          "total": 11,
          "zones": {
            "title": 0,
            "body": 11,
            "menu": 0,
            "footer": 0
          },
          "pages": [
            "https://ascensionpilates.com/"
          ]
        },
        "lineup": {
          "total": 1,
          "zones": {
            "title": 0,
            "body": 1,
            "menu": 0,
            "footer": 0
          },
          "pages": [
            "https://ascensionpilates.com/"
          ]
        },
        "acts": {
          "total": 2,
          "zones": {
            "title": 0,
            "body": 2,
            "menu": 0,
            "footer": 0
          },
          "pages": [
            "https://ascensionpilates.com/"
          ]
        }
      },
      "emails": [
        "info@ascensionpilates.com"
      ],
      "phones": [
        "555-555-5555"
      ],
      "socials": [
        "https://www.instagram.com/p/DM-sRQWxx6p/",
        "https://www.instagram.com/p/DM0j-ncxngI/",
        "https://www.instagram.com/p/DM5-GBNS-jC/",
        "https://www.instagram.com/p/DM5jk51s-nA/",
        "https://www.instagram.com/p/DM73piUsqbp/",
        "https://www.instagram.com/p/DN1LPywZD0D/",
        "https://www.instagram.com/p/DN3sMPT5DR_/",
        "https://www.instagram.com/p/DN88iZDElvP/",
        "https://www.instagram.com/p/DNGxnYVyoyG/",
        "https://www.instagram.com/p/DNJB366Nc63/",
        "https://www.instagram.com/p/DNN9uGLtVRq/",
        "https://www.instagram.com/p/DNQ7D6XxrII/",
        "https://www.instagram.com/p/DNTsXIsytdT/",
        "https://www.instagram.com/p/DN_IfVRDW6W/",
        "https://www.instagram.com/p/DNbqZBoS2Nv/",
        "https://www.instagram.com/p/DNdptkMtdM5/",
        "https://www.instagram.com/p/DNjHgRmSTzb/",
        "https://www.instagram.com/p/DNlXCdZtzP8/",
        "https://www.instagram.com/p/DNqW1Gzt2Rt/",
        "https://www.instagram.com/p/DNtECy3Wju9/",
        "https://www.instagram.com/p/DO6FZk_jTAV/",
        "https://www.instagram.com/p/DO9MNqfEuSd/",
        "https://www.instagram.com/p/DOD-r96Df3w/",
        "https://www.instagram.com/p/DOD5gkJjTdw/",
        "https://www.instagram.com/p/DOEGjjTjSEs/",
        "https://www.instagram.com/p/DOL9A6vjcE9/",
        "https://www.instagram.com/p/DOWXJOHDZRa/",
        "https://www.instagram.com/p/DOY0oZKDZo8/",
        "https://www.instagram.com/p/DOebwg2EgkF/",
        "https://www.instagram.com/p/DOoKrsHjWfB/",
        "https://www.instagram.com/reel/DN8OyQcDUUD/",
        "https://www.instagram.com/reel/DNBuKvXSaF_/",
        "https://www.instagram.com/reel/DNhAx_DNUsM/",
        "https://www.instagram.com/reel/DNn72ACt4E_/",
        "https://www.instagram.com/reel/DNx7cwsWgs3/",
        "https://www.instagram.com/reel/DOJrcH5EuTM/",
        "https://www.instagram.com/reel/DObci7cDQxO/",
        "https://www.instagram.com/reel/DOjRnIYEe69/"
      ]
    },
    "https://ascensionpilates.com/class-schedule": {
      "title": "ASCENSION PILATES | Schedule",
      "band_hits": {
        "event": {
          "total": 3,
          "zones": {
            "title": 0,
            "body": 3,
            "menu": 0,
            "footer": 0
          },
          "pages": [
            "https://ascensionpilates.com/class-schedule"
          ]
        },
        "schedule": {
          "total": 2,
          "zones": {
            "title": 1,
            "body": 1,
            "menu": 0,
            "footer": 0
          },
          "pages": [
            "https://ascensionpilates.com/class-schedule"
          ]
        }
      },
      "emails": [
        "info@ascensionpilates.com",
        "questions.info@ascensionpilates.com"
      ],
      "phones": [
        "352-287-2323",
        "555-555-5555"
      ],
      "socials": [
        "https://www.facebook.com/people/Ascension-Pilates-Wellness/61573952457965/",
        "https://www.instagram.com/ascensionpilates/"
      ]
    },
    "https://ascensionpilates.com/contact": {
      "title": "Ascension Pilates & Wellness  in Crystal River, FL",
      "band_hits": {
        "event": {
          "total": 3,
          "zones": {
            "title": 0,
            "body": 3,
            "menu": 0,
            "footer": 0
          },
          "pages": [
            "https://ascensionpilates.com/contact"
          ]
        }
      },
      "emails": [
        "info@ascensionpilates.com",
        "questions.info@ascensionpilates.com"
      ],
      "phones": [
        "352-287-2323",
        "555-555-5555"
      ],
      "socials": [
        "https://www.facebook.com/people/Ascension-Pilates-Wellness/61573952457965/",
        "https://www.instagram.com/ascensionpilates/"
      ]
    },
    "https://ascensionpilates.com/contact/": {
      "title": "Ascension Pilates & Wellness  in Crystal River, FL",
      "band_hits": {
        "event": {
          "total": 3,
          "zones": {
            "title": 0,
            "body": 3,
            "menu": 0,
            "footer": 0
          },
          "pages": [
            "https://ascensionpilates.com/contact/"
          ]
        }
      },
      "emails": [
        "info@ascensionpilates.com",
        "questions.info@ascensionpilates.com"
      ],
      "phones": [
        "352-287-2323",
        "555-555-5555"
      ],
      "socials": [
        "https://www.facebook.com/people/Ascension-Pilates-Wellness/61573952457965/",
        "https://www.instagram.com/ascensionpilates/"
      ]
    },
    "https://ascensionpilates.com/contact-us/": {
      "title": "ASCENSION PILATES | Contact Us",
      "band_hits": {
        "event": {
          "total": 3,
          "zones": {
            "title": 0,
            "body": 3,
            "menu": 0,
            "footer": 0
          },
          "pages": [
            "https://ascensionpilates.com/contact-us/"
          ]
        }
      },
      "emails": [
        "info@ascensionpilates.com",
        "questions.info@ascensionpilates.com"
      ],
      "phones": [
        "352-287-2323",
        "555-555-5555"
      ],
      "socials": [
        "http://instagram.com/",
        "https://facebook.com/",
        "https://www.facebook.com/people/Ascension-Pilates-Wellness/61573952457965/",
        "https://www.instagram.com/ascensionpilates/"
      ]
    },
    "https://ascensionpilates.com/contactus": {
      "title": "Ascension Pilates & Wellness  in Crystal River, FL",
      "band_hits": {
        "event": {
          "total": 3,
          "zones": {
            "title": 0,
            "body": 3,
            "menu": 0,
            "footer": 0
          },
          "pages": [
            "https://ascensionpilates.com/contactus"
          ]
        }
      },
      "emails": [
        "info@ascensionpilates.com",
        "questions.info@ascensionpilates.com"
      ],
      "phones": [
        "352-287-2323",
        "555-555-5555"
      ],
      "socials": [
        "https://www.facebook.com/people/Ascension-Pilates-Wellness/61573952457965/",
        "https://www.instagram.com/ascensionpilates/"
      ]
    },
    "https://ascensionpilates.com/contactus/": {
      "title": "Ascension Pilates & Wellness  in Crystal River, FL",
      "band_hits": {
        "event": {
          "total": 3,
          "zones": {
            "title": 0,
            "body": 3,
            "menu": 0,
            "footer": 0
          },
          "pages": [
            "https://ascensionpilates.com/contactus/"
          ]
        }
      },
      "emails": [
        "info@ascensionpilates.com",
        "questions.info@ascensionpilates.com"
      ],
      "phones": [
        "352-287-2323",
        "555-555-5555"
      ],
      "socials": [
        "https://www.facebook.com/people/Ascension-Pilates-Wellness/61573952457965/",
        "https://www.instagram.com/ascensionpilates/"
      ]
    },
    "https://ascensionpilates.com/about": {
      "title": "Ascension Pilates & Wellness  in Crystal River, FL",
      "band_hits": {
        "event": {
          "total": 3,
          "zones": {
            "title": 0,
            "body": 3,
            "menu": 0,
            "footer": 0
          },
          "pages": [
            "https://ascensionpilates.com/about"
          ]
        }
      },
      "emails": [
        "info@ascensionpilates.com",
        "questions.info@ascensionpilates.com"
      ],
      "phones": [
        "352-287-2323",
        "555-555-5555"
      ],
      "socials": [
        "https://www.facebook.com/people/Ascension-Pilates-Wellness/61573952457965/",
        "https://www.instagram.com/ascensionpilates/"
      ]
    },
    "https://ascensionpilates.com/about/": {
      "title": "Ascension Pilates & Wellness  in Crystal River, FL",
      "band_hits": {
        "event": {
          "total": 3,
          "zones": {
            "title": 0,
            "body": 3,
            "menu": 0,
            "footer": 0
          },
          "pages": [
            "https://ascensionpilates.com/about/"
          ]
        }
      },
      "emails": [
        "info@ascensionpilates.com",
        "questions.info@ascensionpilates.com"
      ],
      "phones": [
        "352-287-2323",
        "555-555-5555"
      ],
      "socials": [
        "https://www.facebook.com/people/Ascension-Pilates-Wellness/61573952457965/",
        "https://www.instagram.com/ascensionpilates/"
      ]
    },
    "https://ascensionpilates.com/about-us": {
      "title": "Ascension Pilates & Wellness  in Crystal River, FL",
      "band_hits": {
        "event": {
          "total": 3,
          "zones": {
            "title": 0,
            "body": 3,
            "menu": 0,
            "footer": 0
          },
          "pages": [
            "https://ascensionpilates.com/about-us"
          ]
        }
      },
      "emails": [
        "info@ascensionpilates.com",
        "questions.info@ascensionpilates.com"
      ],
      "phones": [
        "352-287-2323",
        "555-555-5555"
      ],
      "socials": [
        "https://www.facebook.com/people/Ascension-Pilates-Wellness/61573952457965/",
        "https://www.instagram.com/ascensionpilates/"
      ]
    },
    "https://ascensionpilates.com/about-us/": {
      "title": "Ascension Pilates & Wellness  in Crystal River, FL",
      "band_hits": {
        "event": {
          "total": 3,
          "zones": {
            "title": 0,
            "body": 3,
            "menu": 0,
            "footer": 0
          },
          "pages": [
            "https://ascensionpilates.com/about-us/"
          ]
        }
      },
      "emails": [
        "info@ascensionpilates.com",
        "questions.info@ascensionpilates.com"
      ],
      "phones": [
        "352-287-2323",
        "555-555-5555"
      ],
      "socials": [
        "https://www.facebook.com/people/Ascension-Pilates-Wellness/61573952457965/",
        "https://www.instagram.com/ascensionpilates/"
      ]
    },
    "https://ascensionpilates.com/visit": {
      "title": "Ascension Pilates & Wellness  in Crystal River, FL",
      "band_hits": {
        "event": {
          "total": 3,
          "zones": {
            "title": 0,
            "body": 3,
            "menu": 0,
            "footer": 0
          },
          "pages": [
            "https://ascensionpilates.com/visit"
          ]
        }
      },
      "emails": [
        "info@ascensionpilates.com",
        "questions.info@ascensionpilates.com"
      ],
      "phones": [
        "352-287-2323",
        "555-555-5555"
      ],
      "socials": [
        "https://www.facebook.com/people/Ascension-Pilates-Wellness/61573952457965/",
        "https://www.instagram.com/ascensionpilates/"
      ]
    },
    "https://ascensionpilates.com/visit/": {
      "title": "Ascension Pilates & Wellness  in Crystal River, FL",
      "band_hits": {
        "event": {
          "total": 3,
          "zones": {
            "title": 0,
            "body": 3,
            "menu": 0,
            "footer": 0
          },
          "pages": [
            "https://ascensionpilates.com/visit/"
          ]
        }
      },
      "emails": [
        "info@ascensionpilates.com",
        "questions.info@ascensionpilates.com"
      ],
      "phones": [
        "352-287-2323",
        "555-555-5555"
      ],
      "socials": [
        "https://www.facebook.com/people/Ascension-Pilates-Wellness/61573952457965/",
        "https://www.instagram.com/ascensionpilates/"
      ]
    },
    "https://ascensionpilates.com/location": {
      "title": "Ascension Pilates & Wellness  in Crystal River, FL",
      "band_hits": {
        "event": {
          "total": 3,
          "zones": {
            "title": 0,
            "body": 3,
            "menu": 0,
            "footer": 0
          },
          "pages": [
            "https://ascensionpilates.com/location"
          ]
        }
      },
      "emails": [
        "info@ascensionpilates.com",
        "questions.info@ascensionpilates.com"
      ],
      "phones": [
        "352-287-2323",
        "555-555-5555"
      ],
      "socials": [
        "https://www.facebook.com/people/Ascension-Pilates-Wellness/61573952457965/",
        "https://www.instagram.com/ascensionpilates/"
      ]
    },
    "https://ascensionpilates.com/location/": {
      "title": "Ascension Pilates & Wellness  in Crystal River, FL",
      "band_hits": {
        "event": {
          "total": 3,
          "zones": {
            "title": 0,
            "body": 3,
            "menu": 0,
            "footer": 0
          },
          "pages": [
            "https://ascensionpilates.com/location/"
          ]
        }
      },
      "emails": [
        "info@ascensionpilates.com",
        "questions.info@ascensionpilates.com"
      ],
      "phones": [
        "352-287-2323",
        "555-555-5555"
      ],
      "socials": [
        "https://www.facebook.com/people/Ascension-Pilates-Wellness/61573952457965/",
        "https://www.instagram.com/ascensionpilates/"
      ]
    },
    "https://ascensionpilates.com/directions": {
      "title": "Ascension Pilates & Wellness  in Crystal River, FL",
      "band_hits": {
        "event": {
          "total": 3,
          "zones": {
            "title": 0,
            "body": 3,
            "menu": 0,
            "footer": 0
          },
          "pages": [
            "https://ascensionpilates.com/directions"
          ]
        }
      },
      "emails": [
        "info@ascensionpilates.com",
        "questions.info@ascensionpilates.com"
      ],
      "phones": [
        "352-287-2323",
        "555-555-5555"
      ],
      "socials": [
        "https://www.facebook.com/people/Ascension-Pilates-Wellness/61573952457965/",
        "https://www.instagram.com/ascensionpilates/"
      ]
    },
    "https://ascensionpilates.com/directions/": {
      "title": "Ascension Pilates & Wellness  in Crystal River, FL",
      "band_hits": {
        "event": {
          "total": 3,
          "zones": {
            "title": 0,
            "body": 3,
            "menu": 0,
            "footer": 0
          },
          "pages": [
            "https://ascensionpilates.com/directions/"
          ]
        }
      },
      "emails": [
        "info@ascensionpilates.com",
        "questions.info@ascensionpilates.com"
      ],
      "phones": [
        "352-287-2323",
        "555-555-5555"
      ],
      "socials": [
        "https://www.facebook.com/people/Ascension-Pilates-Wellness/61573952457965/",
        "https://www.instagram.com/ascensionpilates/"
      ]
    }
  }
}